Workbook

Sheet DATOS LUZ
B2: DATOS DE LA FACTURA | E2: PRECIO POR COMERCIALIZADORA SIN DESGLOSE
G4: 24 Hora | H4: Precio de Mercado
B5: DIAS DE FACTURACIÓN | C5: 31 | E5: GanaEnergía | G5: =GanaEnergía24H!H33 -> 200.79896 | H5: =GanaEnergíaPDM!H35 -> 171.61482
G6: Impulsa 24h | H6: -
B7: POTENCIA CONTRATADA | C7: 5 | E7: Iberdrola | G7: =IberdrolaIMPULSA!H33 -> 198.80552 | H7: -
G8: Fijo24h CP | H8: Fijo24h SP
B9: CONSUMO DE ENERGÍA | C9: 1066 | E9: Endesa | G9: =EndesaFIJA24HCP!H33 -> 206.49046 | H9: =EndesaFIJA24HSP!H33 -> 206.49046
G10: LuzPorUso | H10: -
B11: ACTIVAR SVA | C11: SI | E11: Naturgy | G11: =NaturgyPORUSO!H33 -> 195.80888 | H11: -
B13: IMPUESTO (%) | C13: 0.21 | E13: AHORROS MENSUALES Y ANUALES
E14: Iberdrola | F14: Naturgy | G14: Endesa CP | H14: Endesa SP | I14: GanaEnergía | J14: Gana Indexado
B15: IMPORTE FACTURA LUZ | C15: 169.41 | E15: =IberdrolaIMPULSA!H37 -> -29.39552 | F15: =NaturgyPORUSO!H37 -> -26.398879 | G15: =EndesaFIJA24HCP!H37 -> -37.08046 | H15: =EndesaFIJA24HSP!H37 -> -37.08046 | I15: =GanaEnergía24H!H37 -> -31.38896 | J15: =GanaEnergíaPDM!H39 -> -2.2048238
E16: =IberdrolaIMPULSA!H39 -> -352.74624 | F16: =NaturgyPORUSO!H39 -> -316.78654 | G16: =EndesaFIJA24HCP!H39 -> -444.96552 | H16: =EndesaFIJA24HSP!H39 -> -444.96552 | I16: =GanaEnergía24H!H39 -> -376.66752 | J16: =GanaEnergíaPDM!H41 -> -26.457886
B18: TITULAR | C18: -
B20: Nº CUPS | C20: -
B22: PRECIOS POR COMERCIALIZADORA
C24: POTENCIA | E24: ENERGÍA
C25: P1 | D25: P2 | E25: CON SVA | F25: SIN SVA | H25: PRECIO SVA
B26: Iberdrola | C26: 0.124 | D26: 0.062 | E26: 0.117 | F26: 0.124 | H26: 4.48
C27: P1 | D27: P2 | E27: CON SVA | F27: SIN SVA | H27: PRECIO SVA
B28: Naturgy | C28: 0.123 | D28: 0.061562 | E28: 0.112 | F28: 0.112 | H28: 8.48
C29: P1 | D29: P2 | E29: CON SVA | F29: SIN SVA | H29: PRECIO SVA
B30: Fija 24h Endesa CP | C30: 0.0913 | D30: 0.0913 | E30: 0.123 | F30: 0.127 | H30: 4.77
B31: Fija 24h Endesa SP | C31: 0.0913 | D31: 0.0913 | E31: 0.123 | F31: 0.127 | H31: 4.77
C32: P1 | D32: P2 | E32: SIN SVA | H32: PRECIO SVA
B33: GanaEnergía | C33: 0.089434 | D33: 0.089434 | E33: 0.119 | H33: 5.18
B34: GanaEnergía Indexado | C34: 0.075903 | D34: 0.001988 | E34: 0.105 | F34: 0.125 | G34: 0.191 | H34: 5.18

Sheet IberdrolaIMPULSA
B6: TITULAR DE FACTURACIÓN | D6: ='DATOS LUZ'!C18 -> -
B8: Nº CUPS | D8: ='DATOS LUZ'!C20 -> -
B10: PRODUCTO | D10: Plan Impulsa 24h
B12: PERMANENCIA | D12: NO
B14: TÉRMINO DE POTENCIA
B15: KW | C15: DIAS | D15: €/KW/DIA | H15: IMPORTE
B16: ='DATOS LUZ'!C7 -> 5 | C16: ='DATOS LUZ'!C5 -> 31 | D16: ='DATOS LUZ'!C26 -> 0.124 | E16: P1 | F16: __________________________________________ | H16: =B16*C16*D16 -> 19.22
B17: ='DATOS LUZ'!C7 -> 5 | C17: ='DATOS LUZ'!C5 -> 31 | D17: ='DATOS LUZ'!D26 -> 0.062 | E17: P2 | F17: __________________________________________ | H17: =B17*C17*D17 -> 9.61
B19: TÉRMINO DE ENERGÍA
B20: KW/H | C20: PRECIO KW/H
B21: ='DATOS LUZ'!C9 -> 1066 | C21: {=IFERROR(INDEX('DATOS LUZ'!E26:F26,1,MATCH('DATOS LUZ'!C11,{"SI";"NO"},0)),"")} -> 0.117 | D21: P1 | E21: ________________________________________________________ | H21: =B21*C21 -> 124.722
B23: IMPUESTO SOBRE ELECTRICIDAD
B24: =H16+H17+H21 -> 153.552 | C24: x0,5%___________________________________________________________________ | H24: =B24*0.05 -> 7.6776
B26: IMPUESTOS Y OTROS
C27: alquiler de equipos | D27: ________________________________________________________ | H27: 0.85
B29: SVA | C29: Pack Iberdrola | D29: ________________________________________________________ | H29: =IF('DATOS LUZ'!C11="SI",'DATOS LUZ'!H26,0) -> 4.48
B31: I.V.A. | C31: =B24 -> 153.552 | D31: ________________________________________________________ | H31: =C31*'DATOS LUZ'!C13 -> 32.24592
B33: TOTAL | C33: ________________________________________________________________________ | H33: =H16+H17+H21+H24+H27+H31+H29 -> 198.80552
B35: Importe FACTURA Cliente con su actual comercializadora actualizado a día de hoy | H35: ='DATOS LUZ'!C15 -> 169.41
B37: Ahorro estimado en esta Factura | D37: ________________________________________________________ | H37: =H35-H33 -> -29.39552
B39: Ahorro estimado anual | D39: ________________________________________________________ | H39: =H37*12 -> -352.74624

Sheet NaturgyPORUSO
B6: TITULAR DE FACTURACIÓN | D6: ='DATOS LUZ'!C18 -> -
B8: Nº CUPS | D8: ='DATOS LUZ'!C20 -> -
B10: PRODUCTO | D10: Luz Por Uso
B12: PERMANENCIA | D12: NO
B14: TÉRMINO DE POTENCIA
B15: KW | C15: DIAS | D15: €/KW/DIA | H15: IMPORTE
B16: ='DATOS LUZ'!C7 -> 5 | C16: ='DATOS LUZ'!C5 -> 31 | D16: ='DATOS LUZ'!C28 -> 0.123 | E16: P1 | F16: __________________________________________ | H16: =B16*C16*D16 -> 19.065
B17: ='DATOS LUZ'!C7 -> 5 | C17: ='DATOS LUZ'!C5 -> 31 | D17: ='DATOS LUZ'!D28 -> 0.061562 | E17: P2 | F17: __________________________________________ | H17: =B17*C17*D17 -> 9.54211
B19: TÉRMINO DE ENERGÍA
B20: KW/H | C20: PRECIO KW/H
B21: ='DATOS LUZ'!C9 -> 1066 | C21: {=IFERROR(INDEX('DATOS LUZ'!E28:F28,1,MATCH('DATOS LUZ'!C11,{"SI";"NO"},0)),"")} -> 0.112 | D21: P1 | E21: ________________________________________________________ | H21: =B21*C21 -> 119.392
B23: IMPUESTO SOBRE ELECTRICIDAD
B24: =H16+H17+H21 -> 147.99911 | C24: x0,5%___________________________________________________________________ | H24: =B24*0.05 -> 7.3999555
B26: IMPUESTOS Y OTROS
C27: alquiler de equipos | D27: ________________________________________________________ | H27: 0.85
B29: SVA | C29: ServiElectric | D29: ________________________________________________________ | H29: =IF('DATOS LUZ'!C11="SI",'DATOS LUZ'!H28,0) -> 8.48
B31: I.V.A. | C31: =B24 -> 147.99911 | D31: ________________________________________________________ | H31: =C31*'DATOS LUZ'!C13 -> 31.079813
B33: TOTAL | C33: ________________________________________________________________________ | H33: =H16+H17+H21+H24+H27+H31+H29 -> 195.80888
B35: Importe FACTURA Cliente con su actual comercializadora actualizado a día de hoy | H35: ='DATOS LUZ'!C15 -> 169.41
B37: Ahorro estimado en esta Factura | D37: ________________________________________________________ | H37: =H35-H33 -> -26.398879
B39: Ahorro estimado anual | D39: ________________________________________________________ | H39: =H37*12 -> -316.78654

Sheet EndesaFIJA24HSP
B6: TITULAR DE FACTURACIÓN | D6: ='DATOS LUZ'!C18 -> -
B8: Nº CUPS | D8: ='DATOS LUZ'!C20 -> -
B10: PRODUCTO | D10: Fija 24h Endesa
B12: PERMANENCIA | D12: NO
B14: TÉRMINO DE POTENCIA
B15: KW | C15: DIAS | D15: €/KW/DIA | H15: IMPORTE
B16: ='DATOS LUZ'!C7 -> 5 | C16: ='DATOS LUZ'!C5 -> 31 | D16: ='DATOS LUZ'!C31 -> 0.0913 | E16: P1 | F16: __________________________________________ | H16: =B16*C16*D16 -> 14.1515
B17: ='DATOS LUZ'!C7 -> 5 | C17: ='DATOS LUZ'!C5 -> 31 | D17: ='DATOS LUZ'!D31 -> 0.0913 | E17: P2 | F17: __________________________________________ | H17: =B17*C17*D17 -> 14.1515
B19: TÉRMINO DE ENERGÍA
B20: KW/H | C20: PRECIO KW/H
B21: ='DATOS LUZ'!C9 -> 1066 | C21: {=IFERROR(INDEX('DATOS LUZ'!E31:F31,1,MATCH('DATOS LUZ'!C11,{"SI";"NO"},0)),"")} -> 0.123 | D21: P1 | E21: ________________________________________________________ | H21: =B21*C21 -> 131.118
B23: IMPUESTO SOBRE ELECTRICIDAD
B24: =H16+H17+H21 -> 159.421 | C24: x0,5%___________________________________________________________________ | H24: =B24*0.05 -> 7.97105
B26: IMPUESTOS Y OTROS
C27: alquiler de equipos | D27: ________________________________________________________ | H27: 0.85
B29: SVA | C29: Protección 360 | D29: ________________________________________________________ | H29: =IF('DATOS LUZ'!C11="SI",'DATOS LUZ'!H30,0) -> 4.77
B31: I.V.A. | C31: =B24 -> 159.421 | D31: ________________________________________________________ | H31: =C31*'DATOS LUZ'!C13 -> 33.47841
B33: TOTAL | C33: ________________________________________________________________________ | H33: =H16+H17+H21+H24+H27+H31+H29 -> 206.49046
B35: Importe FACTURA Cliente con su actual comercializadora actualizado a día de hoy | H35: ='DATOS LUZ'!C15 -> 169.41
B37: Ahorro estimado en esta Factura | D37: ________________________________________________________ | H37: =H35-H33 -> -37.08046
B39: Ahorro estimado anual | D39: ________________________________________________________ | H39: =H37*12 -> -444.96552

Sheet EndesaFIJA24HCP
B6: TITULAR DE FACTURACIÓN | D6: ='DATOS LUZ'!C18 -> -
B8: Nº CUPS | D8: ='DATOS LUZ'!C20 -> -
B10: PRODUCTO | D10: Fija 24h Endesa
B12: PERMANENCIA | D12: SÍ
B14: TÉRMINO DE POTENCIA
B15: KW | C15: DIAS | D15: €/KW/DIA | H15: IMPORTE
B16: ='DATOS LUZ'!C7 -> 5 | C16: ='DATOS LUZ'!C5 -> 31 | D16: ='DATOS LUZ'!C30 -> 0.0913 | E16: P1 | F16: __________________________________________ | H16: =B16*C16*D16 -> 14.1515
B17: ='DATOS LUZ'!C7 -> 5 | C17: ='DATOS LUZ'!C5 -> 31 | D17: ='DATOS LUZ'!D30 -> 0.0913 | E17: P2 | F17: __________________________________________ | H17: =B17*C17*D17 -> 14.1515
B19: TÉRMINO DE ENERGÍA
B20: KW/H | C20: PRECIO KW/H
B21: ='DATOS LUZ'!C9 -> 1066 | C21: {=IFERROR(INDEX('DATOS LUZ'!E30:F30,1,MATCH('DATOS LUZ'!C11,{"SI";"NO"},0)),"")} -> 0.123 | D21: P1 | E21: ________________________________________________________ | H21: =B21*C21 -> 131.118
B23: IMPUESTO SOBRE ELECTRICIDAD
B24: =H16+H17+H21 -> 159.421 | C24: x0,5%___________________________________________________________________ | H24: =B24*0.05 -> 7.97105
B26: IMPUESTOS Y OTROS
C27: alquiler de equipos | D27: ________________________________________________________ | H27: 0.85
B29: SVA | C29: Protección 360 | D29: ________________________________________________________ | H29: =IF('DATOS LUZ'!C11="SI",'DATOS LUZ'!H30,0) -> 4.77
B31: I.V.A. | C31: =B24 -> 159.421 | D31: ________________________________________________________ | H31: =C31*'DATOS LUZ'!C13 -> 33.47841
B33: TOTAL | C33: ________________________________________________________________________ | H33: =H16+H17+H21+H24+H27+H31+H29 -> 206.49046
B35: Importe FACTURA Cliente con su actual comercializadora actualizado a día de hoy | H35: ='DATOS LUZ'!C15 -> 169.41
B37: Ahorro estimado en esta Factura | D37: ________________________________________________________ | H37: =H35-H33 -> -37.08046
B39: Ahorro estimado anual | D39: ________________________________________________________ | H39: =H37*12 -> -444.96552

Sheet GanaEnergía24H
B6: TITULAR DE FACTURACIÓN | D6: ='DATOS LUZ'!C18 -> -
B8: Nº CUPS | D8: ='DATOS LUZ'!C20 -> -
B10: PRODUCTO | D10: Plan 24 Horas
B12: PERMANENCIA | D12: NO
B14: TÉRMINO DE POTENCIA
B15: KW | C15: DIAS | D15: €/KW/DIA | H15: IMPORTE
B16: ='DATOS LUZ'!C7 -> 5 | C16: ='DATOS LUZ'!C5 -> 31 | D16: ='DATOS LUZ'!C33 -> 0.089434 | E16: P1 | F16: __________________________________________ | H16: =B16*C16*D16 -> 13.86227
B17: ='DATOS LUZ'!C7 -> 5 | C17: ='DATOS LUZ'!C5 -> 31 | D17: ='DATOS LUZ'!D33 -> 0.089434 | E17: P2 | F17: __________________________________________ | H17: =B17*C17*D17 -> 13.86227
B19: TÉRMINO DE ENERGÍA
B20: KW/H | C20: PRECIO KW/H
B21: ='DATOS LUZ'!C9 -> 1066 | C21: ='DATOS LUZ'!E33 -> 0.119 | D21: P1 | E21: ________________________________________________________ | H21: =B21*C21 -> 126.854
B23: IMPUESTO SOBRE ELECTRICIDAD
B24: =H16+H17+H21 -> 154.57854 | C24: x0,5%___________________________________________________________________ | H24: =B24*0.05 -> 7.728927
B26: IMPUESTOS Y OTROS
C27: alquiler de equipos | D27: ________________________________________________________ | H27: 0.85
B29: SVA | C29: Serv. Gana | D29: ________________________________________________________ | H29: =IF('DATOS LUZ'!C11="SI",'DATOS LUZ'!H33,0) -> 5.18
B31: I.V.A. | C31: =B24 -> 154.57854 | D31: ________________________________________________________ | H31: =C31*'DATOS LUZ'!C13 -> 32.461493
B33: TOTAL | C33: ________________________________________________________________________ | H33: =H16+H17+H21+H24+H27+H31+H29 -> 200.79896
B35: Importe FACTURA Cliente con su actual comercializadora actualizado a día de hoy | H35: ='DATOS LUZ'!C15 -> 169.41
B37: Ahorro estimado en esta Factura | D37: ________________________________________________________ | H37: =H35-H33 -> -31.38896
B39: Ahorro estimado anual | D39: ________________________________________________________ | H39: =H37*12 -> -376.66752

Sheet GanaEnergíaPDM
B6: TITULAR DE FACTURACIÓN | D6: ='DATOS LUZ'!C18 -> -
B8: Nº CUPS | D8: ='DATOS LUZ'!C20 -> -
B10: PRODUCTO | D10: Plan Precio de Mercado
B12: PERMANENCIA | D12: NO
B14: TÉRMINO DE POTENCIA
B15: KW | C15: DIAS | D15: €/KW/DIA | H15: IMPORTE
B16: ='DATOS LUZ'!C7 -> 5 | C16: ='DATOS LUZ'!C5 -> 31 | D16: ='DATOS LUZ'!C34 -> 0.075903 | E16: P1 | F16: __________________________________________ | H16: =B16*C16*D16 -> 11.764965
B17: ='DATOS LUZ'!C7 -> 5 | C17: ='DATOS LUZ'!C5 -> 31 | D17: ='DATOS LUZ'!D34 -> 0.001988 | E17: P2 | F17: __________________________________________ | H17: =B17*C17*D17 -> 0.30814
B19: TÉRMINO DE ENERGÍA
B20: KW/H | C20: PRECIO KW/H
B21: ='DATOS LUZ'!C9*23% -> 245.18 | C21: ='DATOS LUZ'!G34 -> 0.191 | D21: P1 | E21: ________________________________________________________ | H21: =B21*C21 -> 46.82938
B22: ='DATOS LUZ'!C9*24% -> 255.84 | C22: ='DATOS LUZ'!F34 -> 0.125 | D22: P2 | E22: ________________________________________________________ | H22: =B22*C22 -> 31.98
B23: ='DATOS LUZ'!C9*53% -> 564.98 | C23: ='DATOS LUZ'!E34 -> 0.105 | D23: P3 | E23: ________________________________________________________ | H23: =B23*C23 -> 59.3229
B25: IMPUESTO SOBRE ELECTRICIDAD
B26: =H16+H17+H21 -> 58.902485 | C26: x5,11%___________________________________________________________________ | H26: =B26*0.0511 -> 3.009917
B28: IMPUESTOS Y OTROS
C29: alquiler de equipos | D29: ________________________________________________________ | H29: 0.85
B31: SVA | C31: Serv. Gana | D31: ________________________________________________________ | H31: =IF('DATOS LUZ'!C11="SI",'DATOS LUZ'!H34,0) -> 5.18
B33: I.V.A. | C33: =B26 -> 58.902485 | D33: ________________________________________________________ | H33: =C33*'DATOS LUZ'!C13 -> 12.369522
B35: TOTAL | C35: ________________________________________________________________________ | H35: =H16+H17+H21+H22+H23+H26+H29+H33+H31 -> 171.61482
B37: Importe FACTURA Cliente con su actual comercializadora actualizado a día de hoy | H37: ='DATOS LUZ'!C15 -> 169.41
B39: Ahorro estimado en esta Factura | D39: ________________________________________________________ | H39: =H37-H35 -> -2.2048238
B41: Ahorro estimado anual | D41: ________________________________________________________ | H41: =H39*12 -> -26.457886

Sheet DATOS GAS
B2: DATOS DE LA FACTURA | E2: PRECIO POR COMERCIALIZADORA SIN DESGLOSE
G4: Gas GanaEnergia
B5: DIAS DE FACTURACIÓN | C5: 0 | E5: GanaEnergía | G5: =GanaEnergíaGAS!H32 -> 0.85
G6: Gas Iberdrola
B7: POTENCIA CONTRATADA | C7: RL1 | E7: Iberdrola | G7: =IberdrolaGAS!H32 -> 0.85
G8: Gas Endesa
B9: CONSUMO DE ENERGÍA | C9: 0 | E9: Endesa | G9: =EndesaGAS!H32 -> 0.85
G10: Gas Naturgy
B11: ACTIVAR SVA | C11: NO | E11: Naturgy | G11: =NaturgyGAS!H32 -> 0.85
B13: IMPUESTO (%) | C13: 0.21 | E13: AHORROS MENSUALES Y ANUALES
E14: Iberdrola | F14: Naturgy | G14: Endesa | H14: GanaEnergía
B15: IMPORTE FACTURA GAS | C15: 0 | E15: =IberdrolaGAS!H36 -> -0.85 | F15: =NaturgyGAS!H36 -> -0.85 | G15: =EndesaGAS!H36 -> -0.85 | H15: =GanaEnergíaGAS!H36 -> -0.85
E16: =IberdrolaGAS!H38 -> -10.2 | F16: =NaturgyGAS!H38 -> -10.2 | G16: =EndesaGAS!H38 -> -10.2 | H16: =GanaEnergíaGAS!H38 -> -10.2
B18: TITULAR | C18: -
B20: Nº CUPS | C20: -
B22: PRECIOS POR COMERCIALIZADORA
C24: T. FIJOS | F24: T. VARIABLE | I24: SVA Gas
C25: RL1 | D25: RL2 | E25: RL3 | F25: kW / RL1 | G25: kW / RL2 | H25: kW / RL3 | I25: Precio
B26: Iberdrola | C26: 0.2112 | D26: 0.3606 | E26: 0.6945 | F26: 0.1024 | G26: 0.1013 | H26: 0.1013 | I26: 9.95
B28: Naturgy | C28: 0.169342 | D28: 0.300815 | E28: 0.649635 | F28: 0.079533 | G28: 0.077434 | H28: 0.073993 | I28: 11.81
B30: Endesa | C30: 0.2316 | D30: 0.4709 | E30: 0.9894 | F30: 0.0736 | G30: 0.0697 | H30: 0.0643 | I30: 9.09
B32: GanaEnergía | C32: 0.126 | D32: 0.2616 | E32: 0.583 | F32: 0.061 | G32: 0.0589 | H32: 0.0555 | I32: 0

Sheet IberdrolaGAS
B6: TITULAR DE FACTURACIÓN | D6: ='DATOS LUZ'!C18 -> -
B8: Nº CUPS | D8: ='DATOS LUZ'!C20 -> -
B10: PRODUCTO | D10: Iberdrola Gas
B12: PERMANENCIA | D12: NO
B14: TÉRMINO FIJO
B15: DIAS | D15: €/KW/DIA | H15: IMPORTE
B16: ='DATOS GAS'!C5 -> 0 | D16: {=IFERROR(INDEX('DATOS GAS'!C26:E26,1,MATCH('DATOS GAS'!C7,{"RL1";"RL2";"RL3"},0)),"")} -> 0.2112 | E16: ='DATOS GAS'!C7 -> RL1 | F16: __________________________________________ | H16: =B16*D16 -> 0
B18: TÉRMINO VARIABLE
B19: KW/H | C19: PRECIO KW/H
B20: ='DATOS GAS'!C9 -> 0 | C20: {=IFERROR(INDEX('DATOS GAS'!F26:H26,1,MATCH('DATOS GAS'!C7,{"RL1";"RL2";"RL3"},0)),"")} -> 0.1024 | D20: ='DATOS GAS'!C7 -> RL1 | E20: ________________________________________________________ | H20: =B20*C20 -> 0
B22: IMPUESTO SOBRE ELECTRICIDAD
B23: =H16+H20 -> 0 | C23: x0,5%___________________________________________________________________ | H23: =B23*0.05 -> 0
B25: IMPUESTOS Y OTROS
C26: alquiler de equipos | D26: ________________________________________________________ | H26: 0.85
B28: SVA | C28: Pack Iberdrola | D28: ________________________________________________________ | H28: =IF('DATOS GAS'!C11="SI",'DATOS GAS'!I26,0) -> 0
B30: I.V.A. | C30: =B23 -> 0 | D30: ________________________________________________________ | H30: =C30*'DATOS GAS'!C13 -> 0
B32: TOTAL | C32: ________________________________________________________________________ | H32: =H16+H20+H23+H26+H30+H28 -> 0.85
B34: Importe FACTURA Cliente con su actual comercializadora actualizado a día de hoy | H34: ='DATOS GAS'!C15 -> 0
B36: Ahorro estimado en esta Factura | D36: ________________________________________________________ | H36: =H34-H32 -> -0.85
B38: Ahorro estimado anual | D38: ________________________________________________________ | H38: =H36*12 -> -10.2

Sheet NaturgyGAS
B6: TITULAR DE FACTURACIÓN | D6: ='DATOS LUZ'!C18 -> -
B8: Nº CUPS | D8: ='DATOS LUZ'!C20 -> -
B10: PRODUCTO | D10: Gas Por Uso
B12: PERMANENCIA | D12: SÍ
B14: TÉRMINO FIJO
B15: DIAS | D15: €/KW/DIA | H15: IMPORTE
B16: ='DATOS GAS'!C5 -> 0 | D16: {=IFERROR(INDEX('DATOS GAS'!C28:E28,1,MATCH('DATOS GAS'!C7,{"RL1";"RL2";"RL3"},0)),"")} -> 0.169342 | E16: ='DATOS GAS'!C7 -> RL1 | F16: __________________________________________ | H16: =B16*D16 -> 0
B18: TÉRMINO VARIABLE
B19: KW/H | C19: PRECIO KW/H
B20: ='DATOS GAS'!C9 -> 0 | C20: {=IFERROR(INDEX('DATOS GAS'!F28:H28,1,MATCH('DATOS GAS'!C7,{"RL1";"RL2";"RL3"},0)),"")} -> 0.079533 | D20: ='DATOS GAS'!C7 -> RL1 | E20: ________________________________________________________ | H20: =B20*C20 -> 0
B22: IMPUESTO SOBRE ELECTRICIDAD
B23: =H16+H20 -> 0 | C23: x0,5%___________________________________________________________________ | H23: =B23*0.05 -> 0
B25: IMPUESTOS Y OTROS
C26: alquiler de equipos | D26: ________________________________________________________ | H26: 0.85
B28: SVA | C28: Servigas | D28: ________________________________________________________ | H28: =IF('DATOS GAS'!C11="SI",'DATOS GAS'!I28,0) -> 0
B30: I.V.A. | C30: =B23 -> 0 | D30: ________________________________________________________ | H30: =C30*'DATOS GAS'!C13 -> 0
B32: TOTAL | C32: ________________________________________________________________________ | H32: =H16+H20+H23+H26+H30+H28 -> 0.85
B34: Importe FACTURA Cliente con su actual comercializadora actualizado a día de hoy | H34: ='DATOS GAS'!C15 -> 0
B36: Ahorro estimado en esta Factura | D36: ________________________________________________________ | H36: =H34-H32 -> -0.85
B38: Ahorro estimado anual | D38: ________________________________________________________ | H38: =H36*12 -> -10.2

Sheet EndesaGAS
B6: TITULAR DE FACTURACIÓN | D6: ='DATOS LUZ'!C18 -> -
B8: Nº CUPS | D8: ='DATOS LUZ'!C20 -> -
B10: PRODUCTO | D10: Endesa Gas
B12: PERMANENCIA | D12: SÍ
B14: TÉRMINO FIJO
B15: DIAS | D15: €/KW/DIA | H15: IMPORTE
B16: ='DATOS GAS'!C5 -> 0 | D16: {=IFERROR(INDEX('DATOS GAS'!C30:E30,1,MATCH('DATOS GAS'!C7,{"RL1";"RL2";"RL3"},0)),"")} -> 0.2316 | E16: ='DATOS GAS'!C7 -> RL1 | F16: __________________________________________ | H16: =B16*D16 -> 0
B18: TÉRMINO VARIABLE
B19: KW/H | C19: PRECIO KW/H
B20: ='DATOS GAS'!C9 -> 0 | C20: {=IFERROR(INDEX('DATOS GAS'!F30:H30,1,MATCH('DATOS GAS'!C7,{"RL1";"RL2";"RL3"},0)),"")} -> 0.0736 | D20: ='DATOS GAS'!C7 -> RL1 | E20: ________________________________________________________ | H20: =B20*C20 -> 0
B22: IMPUESTO SOBRE ELECTRICIDAD
B23: =H16+H20 -> 0 | C23: x0,5%___________________________________________________________________ | H23: =B23*0.05 -> 0
B25: IMPUESTOS Y OTROS
C26: alquiler de equipos | D26: ________________________________________________________ | H26: 0.85
B28: SVA | C28: Protección 360 | D28: ________________________________________________________ | H28: =IF('DATOS GAS'!C11="SI",'DATOS GAS'!I30,0) -> 0
B30: I.V.A. | C30: =B23 -> 0 | D30: ________________________________________________________ | H30: =C30*'DATOS GAS'!C13 -> 0
B32: TOTAL | C32: ________________________________________________________________________ | H32: =H16+H20+H23+H26+H30+H28 -> 0.85
B34: Importe FACTURA Cliente con su actual comercializadora actualizado a día de hoy | H34: ='DATOS GAS'!C15 -> 0
B36: Ahorro estimado en esta Factura | D36: ________________________________________________________ | H36: =H34-H32 -> -0.85
B38: Ahorro estimado anual | D38: ________________________________________________________ | H38: =H36*12 -> -10.2

Sheet GanaEnergíaGAS
B6: TITULAR DE FACTURACIÓN | D6: ='DATOS LUZ'!C18 -> -
B8: Nº CUPS | D8: ='DATOS LUZ'!C20 -> -
B10: PRODUCTO | D10: Gana Gas
B12: PERMANENCIA | D12: NO
B14: TÉRMINO FIJO
B15: DIAS | D15: €/KW/DIA | H15: IMPORTE
B16: ='DATOS GAS'!C5 -> 0 | D16: {=IFERROR(INDEX('DATOS GAS'!C32:E32,1,MATCH('DATOS GAS'!C7,{"RL1";"RL2";"RL3"},0)),"")} -> 0.126 | E16: ='DATOS GAS'!C7 -> RL1 | F16: __________________________________________ | H16: =B16*D16 -> 0
B18: TÉRMINO VARIABLE
B19: KW/H | C19: PRECIO KW/H
B20: ='DATOS GAS'!C9 -> 0 | C20: {=IFERROR(INDEX('DATOS GAS'!F32:H32,1,MATCH('DATOS GAS'!C7,{"RL1";"RL2";"RL3"},0)),"")} -> 0.061 | D20: ='DATOS GAS'!C7 -> RL1 | E20: ________________________________________________________ | H20: =B20*C20 -> 0
B22: IMPUESTO SOBRE ELECTRICIDAD
B23: =H16+H20 -> 0 | C23: x0,5%___________________________________________________________________ | H23: =B23*0.05 -> 0
B25: IMPUESTOS Y OTROS
C26: alquiler de equipos | D26: ________________________________________________________ | H26: 0.85
B28: SVA | C28: GanaEnergía | D28: ________________________________________________________ | H28: =IF('DATOS GAS'!C11="SI",'DATOS GAS'!I32,0) -> 0
B30: I.V.A. | C30: =B23 -> 0 | D30: ________________________________________________________ | H30: =C30*'DATOS GAS'!C13 -> 0
B32: TOTAL | C32: ________________________________________________________________________ | H32: =H16+H20+H23+H26+H30 -> 0.85
B34: Importe FACTURA Cliente con su actual comercializadora actualizado a día de hoy | H34: ='DATOS GAS'!C15 -> 0
B36: Ahorro estimado en esta Factura | D36: ________________________________________________________ | H36: =H34-H32 -> -0.85
B38: Ahorro estimado anual | D38: ________________________________________________________ | H38: =H36*12 -> -10.2
